iQWorkBook/__init__.py
iQWorkBook/actions.py
iQWorkBook/commons.py
iQWorkBook/constants.py
iQWorkBook/widgets.py
iQWorkBook-1.0.1.dist-info/LICENSE
iQWorkBook-1.0.1.dist-info/METADATA
iQWorkBook-1.0.1.dist-info/WHEEL
iQWorkBook-1.0.1.dist-info/top_level.txt
iQWorkBook-1.0.1.dist-info/RECORD
